sympytorch/__init__.py
sympytorch/hide_floats_m.py
sympytorch/py.typed
sympytorch/sympy_module.py
sympytorch-0.1.4.dist-info/LICENSE
sympytorch-0.1.4.dist-info/METADATA
sympytorch-0.1.4.dist-info/WHEEL
sympytorch-0.1.4.dist-info/top_level.txt
sympytorch-0.1.4.dist-info/RECORD
